poetry_monorepo_dependency_plugin/__init__.py
poetry_monorepo_dependency_plugin/path_dependency_remover.py
poetry_monorepo_dependency_plugin/path_dependency_rewriter.py
poetry_monorepo_dependency_plugin/plugin.py
poetry_monorepo_dependency_plugin-1.3.1.dist-info/LICENSE
poetry_monorepo_dependency_plugin-1.3.1.dist-info/METADATA
poetry_monorepo_dependency_plugin-1.3.1.dist-info/WHEEL
poetry_monorepo_dependency_plugin-1.3.1.dist-info/entry_points.txt
poetry_monorepo_dependency_plugin-1.3.1.dist-info/RECORD
