Metadata-Version: 2.3
Name: poetry-monorepo-dependency-plugin
Version: 1.3.1
Summary: Poetry plugin that generates more easily consumable archives for projects in a monorepo structure with path dependencies on other Poetry projects
License: MIT
Author: Eric Konieczny
Author-email: ekoniec1@gmail.com
Requires-Python: >=3.8,<4
Classifier: License :: OSI Approved :: MIT License
Classifier: Programming Language :: Python :: 3
Classifier: Programming Language :: Python :: 3.8
Classifier: Programming Language :: Python :: 3.9
Classifier: Programming Language :: Python :: 3.10
Classifier: Programming Language :: Python :: 3.11
Classifier: Programming Language :: Python :: 3.12
Classifier: Programming Language :: Python :: 3.13
Requires-Dist: cleo (>=2.0.1)
Requires-Dist: poetry (>=1.6)
Requires-Dist: poetry-plugin-export (>=1.5.0)
Project-URL: Repository, https://github.com/TechnologyBrewery/poetry-monorepo-dependency-plugin
